CHANGELOG.md
MANIFEST.in
README.md
setup.py
pu/__init__.py
pu/_version.py
pu/aiotimer.py
pu/autopdb.py
pu/cache.py
pu/datatype.py
pu/dictutil.py
pu/distance.py
pu/event.py
pu/lazydict.py
pu/manager.py
pu/minimist.py
pu/pcap.py
pu/pubsub.py
pu/rcp.py
pu/simplefilter.py
pu/url.py
pu/util.py
pu/yamlfile.py
pu.egg-info/PKG-INFO
pu.egg-info/SOURCES.txt
pu.egg-info/dependency_links.txt
pu.egg-info/top_level.txt
pu/aio/__init__.py
pu/aio/client.py
pu/aio/dummyprotocol.py
pu/aio/timer.py
pu/aio/util.py
pu/aio/virtualprotocol.py
pu/aio/protocols/__init__.py
pu/aio/protocols/basic.py
pu/aio/protocols/cli.py
pu/misc/__init__.py
pu/misc/aiohttp.py
pu/pattern/__init__.py
pu/pattern/observer.py
test/test_dictutil.py
test/test_lazydict.py
test/test_manager.py
test/test_minimist.py
test/test_rcp.py
test/test_simplefilter.py
test/test_url.py
test/test_util.py