Metadata-Version: 2.1
Name: pu
Version: 0.20.1
Summary: Python utils
Home-page: https://github.com/huyx/pu
Author: yuxin
Author-email: ycyuxin@gmail.com
License: GNU Library or Lesser General Public License (LGPL)
Keywords: python,util
Platform: UNKNOWN
Classifier: Programming Language :: Python
Classifier: Programming Language :: Python :: 3
Classifier: Development Status :: 4 - Beta
Classifier: Intended Audience :: Developers
Classifier: License :: OSI Approved :: GNU Library or Lesser General Public License (LGPL)
Classifier: Operating System :: OS Independent
Classifier: Topic :: Software Development :: Libraries :: Python Modules
